pyyarl/__init__.py
pyyarl/decorators.py
pyyarl/rate_limiter.py
pyyarl-1.0.0.dist-info/LICENSE
pyyarl-1.0.0.dist-info/METADATA
pyyarl-1.0.0.dist-info/WHEEL
pyyarl-1.0.0.dist-info/top_level.txt
pyyarl-1.0.0.dist-info/RECORD
