Metadata-Version: 2.1
Name: pyyarl
Version: 1.0.0
Summary: Yet Another Rate Limiter (for Python)
Home-page: https://github.com/jeremyephron/pyyarl
Author: Jeremy Ephron
Author-email: jeremye@cs.stanford.edu
License: UNKNOWN
Platform: UNKNOWN
Classifier: Development Status :: 3 - Alpha
Classifier: Programming Language :: Python
Classifier: Programming Language :: Python :: 3
Classifier: Programming Language :: Python :: 3.7
Classifier: Programming Language :: Python :: 3.8
Classifier: Programming Language :: Python :: 3.9
Classifier: Programming Language :: Python :: 3.10
Classifier: License :: OSI Approved :: MIT License
Classifier: Operating System :: MacOS
Classifier: Operating System :: Unix
